physics/__init__.py
physics/collisions.py
physics/color.py
physics/objects.py
physics/rendering.py
physics/vector.py
physics/world.py
dphysicsengine-0.1.15.dist-info/METADATA
dphysicsengine-0.1.15.dist-info/WHEEL
dphysicsengine-0.1.15.dist-info/top_level.txt
dphysicsengine-0.1.15.dist-info/RECORD
