Metadata-Version: 2.4
Name: dphysicsengine
Version: 0.1.15
Summary: Motor físico para simulaciones
Author-email: David García Díaz <davidgrcdiaz@gmail.com>
Requires-Python: >=3.7
Requires-Dist: pillow==9.1.1
